GT_Utils/EventTrackerGUI.py
GT_Utils/__init__.py
GT_Utils/EventTracker/EventCreator.py
GT_Utils/EventTracker/EventTracker.py
GT_Utils/EventTracker/__init__.py
GT_Utils/FileUtils/FileUtils.py
GT_Utils/FileUtils/__init__.py
GT_Utils/GUI_Utils/FileSaver.py
GT_Utils/GUI_Utils/__init__.py
GT_Utils/GUI_Utils/Group/ConsoleBox.py
GT_Utils/GUI_Utils/Group/GroupBox.py
GT_Utils/GUI_Utils/Group/LineEditGroupBox.py
GT_Utils/GUI_Utils/Group/__init__.py
GT_Utils/GUI_Utils/GroupElement/ComboBox.py
GT_Utils/GUI_Utils/GroupElement/PushButton.py
GT_Utils/GUI_Utils/GroupElement/__init__.py
GT_Utils/GUI_Utils/Window/TabWidget.py
GT_Utils/GUI_Utils/Window/WidgetForTabWidget.py
GT_Utils/GUI_Utils/Window/__init__.py
GT_Utils-1.0.2.dist-info/LICENSE
GT_Utils-1.0.2.dist-info/METADATA
GT_Utils-1.0.2.dist-info/WHEEL
GT_Utils-1.0.2.dist-info/top_level.txt
GT_Utils-1.0.2.dist-info/RECORD
